{
  "promptHash": "f9f8daa8c2bee48a5ede0b6f9a8144e0d2bde8448e9f2897e30ce5365ee21747",
  "roleId": "structurer",
  "model": "opus",
  "rawJson": "{\"candidates\":[{\"approach\":\"사례→원리: '매달 50만 원 계좌 공개' 훅으로 시작해 도시락·차용증 비유로 배당 원리를 깐 뒤, 커버드콜이라는 어려운 개념을 맨 뒤로 미뤄 케이스별로 갈라주는 흐름\",\"outline\":[{\"section\":\"공감형 오프닝 — 내 월배당 계좌부터 공개\",\"goal\":\"시청자가 '나도 매달 현금 꽂히는 그 느낌' 궁금증에 바로 몰입하고 채널 톤에 안심한다\",\"why\":\"인사 직후 자기 계좌·근황 공개 훅이 김짠부 고정 진입로라, 처음 듣는 사람도 '실제 사람 얘기'로 편하게 진입하기 때문\",\"format\":\"explain\"},{\"section\":\"오늘은 딱 이것만 + 좋아요 요청\",\"goal\":\"'배당 원리→커버드콜'까지 오늘의 범위를 알고 학습 부담이 줄어든다\",\"why\":\"무거운 주제를 한 번에 욱여넣지 않고 범위를 좁혀 '머리 안 터진다'고 미리 안심시키는 순서가 필요해서\",\"format\":\"explain\"},{\"section\":\"배당금이 뭔데? — '월세 받는 건물주' 비유\",\"goal\":\"배당=내가 가진 지분에 따라 또박또박 떨어지는 현금이라는 큰 그림을 직관으로 잡는다\",\"why\":\"본론 전 핵심 용어를 일상 비유로 먼저 푸는 것이 진입장벽을 낮추는 김짠부 기본 원칙이라\",\"format\":\"explain\"},{\"section\":\"그럼 월배당 ETF는? — 도시락에 '매달 반찬값 돌려주기'\",\"goal\":\"개별 종목이 아니라 ETF(도시락) 단위로 매달 분배금이 나오는 구조를 이해한다\",\"why\":\"쉬운 비유(도시락)로 직관을 박은 뒤 숫자로 넘어가는 흐름이 이해 흐름상 자연스러워서\",\"format\":\"explain\"},{\"section\":\"매달 50만 원씩 5년·10년 넣으면 실제로 얼마? — 숫자로 계산\",\"goal\":\"적립 금액·기간별로 받는 배당과 쌓이는 자산을 구체 숫자로 체감한다\",\"why\":\"비유로 큰 그림을 잡은 뒤 구체 숫자 계산으로 정밀화하는 김짠부 패턴이고, '끝까지 볼 이유' 미끼도 되기 때문\",\"format\":\"explain\"},{\"section\":\"이제 커버드콜 — '치킨 미리 팔고 쿠폰 받기'\",\"goal\":\"고배당의 정체인 커버드콜 옵션 구조를 겁먹지 않고 한 문장 비유로 이해한다\",\"why\":\"가장 어려운 개념을 맨 뒤로 미뤄 비유·맥락을 충분히 깐 뒤 꺼내는 것이 불안을 줄이는 순서라\",\"format\":\"explain\"},{\"section\":\"일반 월배당 vs 커버드콜 월배당 — 비교 표\",\"goal\":\"배당률·상승여력·원금 흐름이 어떻게 다른지 두 상품을 나란히 본다\",\"why\":\"분배율은 높지만 상승을 일부 포기하는 trade-off가 분명한 2축 비교라 표가 자연스럽게 나오는 섹션\",\"format\":\"table\"},{\"section\":\"그래서 누구한테 맞아요? — 성향별 분기\",\"goal\":\"'당장 현금흐름이 필요한 분'과 '아직 굴릴 시간이 많은 분'이 각자 답을 가져간다\",\"why\":\"투자 영역은 정답이 하나가 아님을 인정하고 상황별로 갈라주는 것이 김짠부 방식이라\",\"format\":\"case\"},{\"section\":\"오개념 박살 — '배당률 높으면 무조건 이득 아닌가요?'\",\"goal\":\"높은 분배율이 원금 까먹기(주가 하락 상쇄)일 수 있다는 함정을 계산으로 깨닫는다\",\"why\":\"시청자가 자연히 품을 오해를 따옴표로 인용하고 '놉놉!'으로 깨는 선제 제거가 핵심 신뢰 장치라\",\"format\":\"explain\"},{\"section\":\"짠부는 이렇게 합니다 + 정리·다음 편 예고\",\"goal\":\"진행자의 솔직한 선택을 보고 핵심을 재요약하며 '노후 현금흐름'이라는 큰 그림으로 안심한다\",\"why\":\"자기 선택 공개→'정리하면' 요약→무거운 후속(세금 등) 예고가 김짠부 마무리 정형이라\",\"format\":\"explain\"}],\"reason\":\"제목의 '매달 50만 원' 시뮬레이션을 훅으로 살리고, 가장 어려운 커버드콜을 비유·숫자·표를 다 깐 뒤 맨 끝에 배치해 '편안하게 듣다 보니 이해됐다'는 북극성을 충족한다. 비교 축이 분명한 곳에만 표, 답이 갈리는 곳에만 케이스를 써 형식 남용을 피했다.\",\"evidence_ids\":[\"title\",\"topic\",\"tone:ETF가 딱 편의점 도시락 같은 거예요\",\"tone:치킨은 똥으로 나오지만, ETF는 미래 내 식비를 해결해줄 겁니다\",\"style:b881012a-a0f9-42ae-95ff-fa36d8685228\"]},{\"approach\":\"공포·오해 해소형: '매달 현금 꽂히는데 왜 다들 위험하대?'라는 시청자 불안을 먼저 소환하고, 커버드콜의 trade-off를 정면으로 안심시키며 오해부터 차례로 박살내는 흐름\",\"outline\":[{\"section\":\"공감형 오프닝 — '월배당 사도 돼요?' 댓글 폭주 소환\",\"goal\":\"내 고민이 다수의 고민임을 알고 '이 영상이 정리해주겠구나' 기대한다\",\"why\":\"시청자가 실제로 많이 보낸 질문을 소환하는 훅이 정보·개념형 편의 전형적 진입로라\",\"format\":\"explain\"},{\"section\":\"겁먹지 마세요 — 오늘 불안 3개를 다 풀어드릴게요 + 좋아요\",\"goal\":\"'위험하다던데' '원금 까먹는다던데' 같은 막연한 공포의 정체를 오늘 다 푼다는 안도를 얻는다\",\"why\":\"어려운 주제 앞에서 학습 부담과 불안을 먼저 낮추는 김짠부식 안심이 본론 몰입을 돕기 때문\",\"format\":\"explain\"},{\"section\":\"배당금 원리부터 — '차용증·월세' 비유로 1분 정리\",\"goal\":\"배당이 어디서 나오는 돈인지(공짜가 아님) 기본 원리를 부담 없이 이해한다\",\"why\":\"공포를 풀려면 먼저 기초 개념이 깔려야 하므로 쉬운 비유 정의를 앞단에 두는 것\",\"format\":\"explain\"},{\"section\":\"불안1 '배당 받는 만큼 주가가 빠진다던데?' — 배당락 해설\",\"goal\":\"배당락이 사기가 아니라 당연한 회계 현상임을 알고 첫 공포를 내려놓는다\",\"why\":\"가장 흔하고 즉각적인 오해를 먼저 짚어 선제 제거하는 misconception 처리 패턴\",\"format\":\"explain\"},{\"section\":\"불안2 '커버드콜은 위험한 옵션 아니에요?' — '치킨 쿠폰' 비유\",\"goal\":\"커버드콜이 도박이 아니라 '상승 일부를 팔아 현금을 당겨오는' 구조임을 이해한다\",\"why\":\"용어가 무서워 생기는 공포라 비유로 직관을 먼저 박아 안심시키는 순서가 필요해서\",\"format\":\"explain\"},{\"section\":\"불안3 '배당률 15%면 개꿀 아니에요?' — 놉놉! 계산으로 증명\",\"goal\":\"초고배당이 상승 포기·원금 잠식과 맞바꾼 결과일 수 있음을 숫자로 납득한다\",\"why\":\"'높으면 무조건 좋다'는 오해를 직접 인용하고 계산으로 박살내는 것이 신뢰의 핵심이라\",\"format\":\"explain\"},{\"section\":\"일반 ETF vs 커버드콜 ETF — 같은 50만 원을 넣으면\",\"goal\":\"총수익(주가+배당) 관점에서 두 선택이 장기적으로 어떻게 벌어지는지 나란히 본다\",\"why\":\"두 상품의 수익 구조 차이가 명확한 2축 비교라 표가 자연스럽게 도출되는 섹션\",\"format\":\"table\"},{\"section\":\"그래서 이런 분께 추천 / 이런 분은 잠깐\",\"goal\":\"현금흐름이 급한 사람과 아직 자산 키울 시간이 많은 사람이 각자 결론을 갖는다\",\"why\":\"공포를 풀어준 뒤 '그래도 만능은 아니다'를 성향별로 갈라주는 것이 정직한 마무리라\",\"format\":\"case\"},{\"section\":\"정리 + '결국 목적은 노후 현금흐름' + 마무리 CTA\",\"goal\":\"핵심 3가지를 재정리하고 큰 그림으로 끌어올려 편안하게 끝맺는다\",\"why\":\"'정리하면' 요약→큰 그림 안심→커피쿠폰 마무리가 김짠부 고정 클로징이라\",\"format\":\"explain\"}],\"reason\":\"같은 주제를 '사례→원리'가 아니라 '공포·오해부터 해소'하는 정반대 접근으로 설계했다. 시청자가 겁먹는 지점(배당락·옵션·초고배당)을 본론의 뼈대로 삼아 하나씩 안심시키며, 표·케이스는 비교·분기가 실재하는 두 섹션에만 붙여 김짠부다움을 지켰다.\",\"evidence_ids\":[\"topic\",\"title\",\"tone:채권은 쉽게 말해서 '차용증'이에요\",\"tone:금리가 연 3%다? 그럼 100만 원 넣어두면 1년 뒤에 3만 원이 그냥 생기는 거예요\",\"style:b881012a-a0f9-42ae-95ff-fa36d8685228\"]}]}",
  "usage": {
    "inTok": 3341,
    "outTok": 1047,
    "cachedInTok": 0
  },
  "recordedAt": "2026-06-30T15:02:23.206Z"
}