[
  {
    "title": "행정규칙 > 우체국예금에 관한 사항 - 국가법령정보센터",
    "url": "https://www.law.go.kr/LSW/admRulLsInfoP.do?admRulSeq=2100000263718",
    "content": "1) 보통예금 : 예입과 지급에 있어서 특별한 조건을 붙이지 아니하고 입출금이 자유로운 예금 · 2) 저축예금 : 개인만을 대상으로 하여 입출금이 자유로운",
    "score": 0.528899,
    "publisher": "law.go.kr",
    "published_at": null
  },
  {
    "title": "저축은행 관련 브리핑 - 금융위원회",
    "url": "https://www.fsc.go.kr/no010103/24462?srchCtgry=&curPage=50&srchKey=&srchText=&srchBeginDt=&srchEndDt=",
    "content": "예금자 보호법에 따라서 원금과 이자를 합쳐 5,000만 원 이하 예금은 어떤 경우에도 전액 보호가 됩니다. 영업정지 된 저축은행의 예금자 불편을 최소화기 위하여 4,500만",
    "score": 0.13634396,
    "publisher": "fsc.go.kr",
    "published_at": null
  },
  {
    "title": "상호저축은행법 시행령 - 국가법령정보센터",
    "url": "https://www.law.go.kr/LSW//lsInfoP.do?lsiSeq=280533&chrClsCd=010202&urlMode=lsInfoP&efYd=20251223&ancYnChk=0",
    "content": "② 금융위원회는 경영지도를 받고 있는 상호저축은행이 법 제24조의15제1항ㆍ제2항 또는 「예금자보호법」 제36조에 따라 영업을 양도하거나 제3자가 그",
    "score": 0.11876296,
    "publisher": "law.go.kr",
    "published_at": null
  },
  {
    "title": "[HWP] 2015 - 금융위원회",
    "url": "https://www.fsc.go.kr/comm/getFile?srvcId=BBSTY1&upperNo=71566&fileTy=ATTACH&fileNo=3",
    "content": "2) 수시입출금식 상품 등 판매시 전체 이자지급 구조표, 금리지급 조건(예치기간, 한도, 최고금리 등), 과거 6개월간 평균지급 금리, 선입선출 등 중요사항 등을 표시(수",
    "score": 0.057774507,
    "publisher": "fsc.go.kr",
    "published_at": null
  },
  {
    "title": "[PDF] 제1차 실무작업반 논의 내용 - 금융위원회",
    "url": "https://www.fsc.go.kr/comm/getFile?srvcId=BBSTY1&upperNo=79526&fileTy=ATTACH&fileNo=10",
    "content": "대상을 '개인'으로 제한 ▚증권사는 자금이체대상 제한이 없는 他특별참가기관보다 많은 규모의 특별참가금(약 4천억원 : 최초 3400억원+추가)을",
    "score": 0.05644935,
    "publisher": "fsc.go.kr",
    "published_at": null
  },
  {
    "title": "[HWP] 1 - 금융위원회",
    "url": "https://www.fsc.go.kr/comm/getFile?srvcId=BBSTY1&upperNo=74144&fileTy=ATTACH&fileNo=3",
    "content": "... 조건을 붙여 혁신금융서비스로 지정(지정일로부터 2년) ※ 부가조건 주요 내용 ◾ 업무위수탁 범위 명확화, 업무 범위에 대한 소비자 보호방안 마련 ◾ 합리적인 업무",
    "score": 0.041684147,
    "publisher": "fsc.go.kr",
    "published_at": null
  }
]