{
  "promptHash": "a904400e729e68d9343d7dca5bca7446deef661a1dc18e661e06b0ac29fbed80",
  "roleId": "thumbnail_maker",
  "model": "opus",
  "rawJson": "{\"candidates\":[{\"thumbnail_layout\":\"검정 배경, 놀란 표정 인물 우측. 좌측 상·하단에 노랑 굵은 메인카피 2줄, 인물 아래 작은 검정박스 2개에 흰/노랑 보조문구.\",\"thumbnail_main\":[\"레버리지 ETF, 장기투자 금지\",\"며칠만 들고 파는 상품이에요\"],\"thumbnail_boxes\":[\"2배·인버스 ETF 정체\",\"왜 오래 들면 손해일까?\"],\"reason\":\"통념 반전 앵글. '장기투자는 무조건 옳다'는 믿음을 뒤집어 레버리지·곱버스는 단기 상품이라는 핵심을 한눈에 던진다. 두 메인 줄 모두 따로 봐도 완성된 경고 메시지다.\",\"evidence_ids\":[\"style:be683a08-cbb6-4d4f-a57f-adf65b7518bc\",\"ref:0a69f51e-43c9-4a31-9355-e5534a920853\",\"tone:v1\"]},{\"thumbnail_layout\":\"검정 배경, 손동작(X 제스처) 인물 좌측. 우측 상·하단 노랑 대형 메인카피, 하단 작은박스 2개는 검정 바탕에 노랑 강조.\",\"thumbnail_main\":[\"10년 묻어두면 수익률 0\",\"오래 들수록 손해 봅니다\"],\"thumbnail_boxes\":[\"곱버스 ETF의 함정\",\"초보가 제일 많이 사요\"],\"reason\":\"숫자·공포 앵글. '오래 들수록 안전하다'는 적립식 상식과 정반대인 '수익률 0' 단언으로 충격을 준다. 구어체 숫자(10년·0)를 명령과 묶는 스타일 사양을 따른다.\",\"evidence_ids\":[\"style:be683a08-cbb6-4d4f-a57f-adf65b7518bc\",\"ref:d4fed5ad-9997-4384-90b6-bb64efa08ca0\"]},{\"thumbnail_layout\":\"검정 배경, 입틀막 놀란 표정 인물 중앙. 상단 노랑 메인 한 줄, 하단 노랑 메인 한 줄로 인물 위·아래 배치. 작은박스 2개는 인물 옆 세로 정렬.\",\"thumbnail_main\":[\"이거 모르고 사면 큰일나요\",\"초보가 제일 많이 하는 실수\"],\"thumbnail_boxes\":[\"레버리지·곱버스 ETF\",\"사기 전에 꼭 보세요\"],\"reason\":\"경고 명령·호기심 앵글. '초보가 제일 많이 하는 실수'로 본인 얘기처럼 끌어당기고, 메인 두 줄을 각각 독립된 후킹으로 세워 클릭 전 불안을 자극한다.\",\"evidence_ids\":[\"style:be683a08-cbb6-4d4f-a57f-adf65b7518bc\",\"ref:2285809a-2559-44c3-9c51-31be159535b8\",\"tone:v1\"]}]}",
  "usage": {
    "inTok": 2811,
    "outTok": 318,
    "cachedInTok": 0
  },
  "recordedAt": "2026-06-25T05:08:20.927Z"
}